setup.cfg
setup.py
j2hc/__init__.py
j2hc/compressors.py
j2hc.egg-info/PKG-INFO
j2hc.egg-info/SOURCES.txt
j2hc.egg-info/dependency_links.txt
j2hc.egg-info/requires.txt
j2hc.egg-info/top_level.txt