Metadata-Version: 1.1
Name: j2hc
Version: 0.1.2
Summary: Jinja2 extension that removes whitespace between HTML tags
Home-page: https://github.com/erthalion/jinja2-htmlcompress
Author: Dmitry Dolgov
Author-email: 9erthalion6@gmail.com
License: UNKNOWN
Download-URL: https://github.com/erthalion/jinja2-htmlcompress/tarball/0.1.2
Keywords: jinja2,html,compress
Platform: UNKNOWN
